{
  "LinearAlgebra\\linear_systems_matrices\\linear_transformations": {
    "la_fig_7": {
      "output_type": "display_data",
      "metadata": {
        "scrapbook": {
          "name": "la_fig_7",
          "mime_prefix": "application/papermill.record/"
        },
        "filenames": {
          "image/png": "C:\\Users\\NatSciTeaching\\Documents\\GitHub\\Mathematics-for-Natural-Sciences-A\\_build\\jupyter_execute\\LinearAlgebra\\linear_systems_matrices\\linear_transformations_9_0.png"
        }
      },
      "data": {
        "application/papermill.record/text/plain": "<Figure size 684x288 with 2 Axes>",
        "application/papermill.record/image/png": null
      }
    },
    "la_fig_1": {
      "output_type": "display_data",
      "metadata": {
        "scrapbook": {
          "name": "la_fig_1",
          "mime_prefix": "application/papermill.record/"
        },
        "filenames": {
          "image/png": "C:\\Users\\NatSciTeaching\\Documents\\GitHub\\Mathematics-for-Natural-Sciences-A\\_build\\jupyter_execute\\LinearAlgebra\\linear_systems_matrices\\linear_transformations_2_0.png"
        }
      },
      "data": {
        "application/papermill.record/text/plain": "<Figure size 684x288 with 2 Axes>",
        "application/papermill.record/image/png": null
      }
    },
    "la_fig_5": {
      "output_type": "display_data",
      "metadata": {
        "scrapbook": {
          "name": "la_fig_5",
          "mime_prefix": "application/papermill.record/"
        },
        "filenames": {
          "image/png": "C:\\Users\\NatSciTeaching\\Documents\\GitHub\\Mathematics-for-Natural-Sciences-A\\_build\\jupyter_execute\\LinearAlgebra\\linear_systems_matrices\\linear_transformations_6_0.png"
        }
      },
      "data": {
        "application/papermill.record/text/plain": "<Figure size 684x288 with 2 Axes>",
        "application/papermill.record/image/png": null
      }
    },
    "la_fig_3": {
      "output_type": "display_data",
      "metadata": {
        "scrapbook": {
          "name": "la_fig_3",
          "mime_prefix": "application/papermill.record/"
        },
        "filenames": {
          "image/png": "C:\\Users\\NatSciTeaching\\Documents\\GitHub\\Mathematics-for-Natural-Sciences-A\\_build\\jupyter_execute\\LinearAlgebra\\linear_systems_matrices\\linear_transformations_4_0.png"
        }
      },
      "data": {
        "application/papermill.record/text/plain": "<Figure size 684x288 with 2 Axes>",
        "application/papermill.record/image/png": null
      }
    },
    "la_fig_6": {
      "output_type": "display_data",
      "metadata": {
        "scrapbook": {
          "name": "la_fig_6",
          "mime_prefix": "application/papermill.record/"
        },
        "filenames": {
          "image/png": "C:\\Users\\NatSciTeaching\\Documents\\GitHub\\Mathematics-for-Natural-Sciences-A\\_build\\jupyter_execute\\LinearAlgebra\\linear_systems_matrices\\linear_transformations_8_0.png"
        }
      },
      "data": {
        "application/papermill.record/text/plain": "<Figure size 720x194.4 with 3 Axes>",
        "application/papermill.record/image/png": null
      }
    },
    "la_fig_2": {
      "output_type": "display_data",
      "metadata": {
        "scrapbook": {
          "name": "la_fig_2",
          "mime_prefix": "application/papermill.record/"
        },
        "filenames": {
          "image/png": "C:\\Users\\NatSciTeaching\\Documents\\GitHub\\Mathematics-for-Natural-Sciences-A\\_build\\jupyter_execute\\LinearAlgebra\\linear_systems_matrices\\linear_transformations_3_0.png"
        }
      },
      "data": {
        "application/papermill.record/text/plain": "<Figure size 684x288 with 2 Axes>",
        "application/papermill.record/image/png": null
      }
    },
    "la_fig_4": {
      "output_type": "display_data",
      "metadata": {
        "scrapbook": {
          "name": "la_fig_4",
          "mime_prefix": "application/papermill.record/"
        },
        "filenames": {
          "image/png": "C:\\Users\\NatSciTeaching\\Documents\\GitHub\\Mathematics-for-Natural-Sciences-A\\_build\\jupyter_execute\\LinearAlgebra\\linear_systems_matrices\\linear_transformations_5_0.png"
        }
      },
      "data": {
        "application/papermill.record/text/plain": "<Figure size 684x288 with 2 Axes>",
        "application/papermill.record/image/png": null
      }
    }
  }
}